flockfile
