Metadata-Version: 2.1
Name: flockfile
Version: 0.1.2
Summary: A simple lock file class based on file locking.
Home-page: https://gitlab.com/rveach/flockfile
Author: Ryan Veach
Author-email: rveach@gmail.com
License: MIT
Project-URL: Source, https://gitlab.com/rveach/flockfile
Project-URL: Tracker, https://gitlab.com/rveach/flockfile/issues
Keywords: Lock,Flock
Platform: UNKNOWN
Classifier: Development Status :: 4 - Beta
Classifier: Intended Audience :: Developers
Classifier: License :: OSI Approved :: MIT License
Classifier: Programming Language :: Python :: 2
Classifier: Programming Language :: Python :: 2.7
Classifier: Programming Language :: Python :: 3
Classifier: Programming Language :: Python :: 3.6
Classifier: Programming Language :: Python :: 3.7
Classifier: Programming Language :: Python :: 3.8
Requires-Python: >=2.7
